aicaller/__init__.py
aicaller/__main__.py
aicaller/conversion.py
aicaller/few_shot_sampler.py
aicaller/loader.py
aicaller/modules.py
aicaller/sample_assembler.py
aicaller/template.py
aicaller/utils.py
aicaller/api/__init__.py
aicaller/api/api.py
aicaller/api/api_async.py
aicaller/api/base.py
aicaller/api/factory.py
aicaller-1.1.4.dist-info/METADATA
aicaller-1.1.4.dist-info/WHEEL
aicaller-1.1.4.dist-info/entry_points.txt
aicaller-1.1.4.dist-info/top_level.txt
aicaller-1.1.4.dist-info/RECORD
