Metadata-Version: 2.4
Name: aicaller
Version: 1.1.4
Summary: Package for using API models. It is designed mainly for experimenting with various models. It allows to easily process Hugging Face datasets, or JSONL/CSV datasets, and send requests to Ollama and OpenAI compatibles APIs with just using simple configuration files.
Author: Martin Dočekal
Project-URL: Repository, https://github.com/mdocekal/ai_caller
Keywords: openai,ollama,api,datasets
Requires-Python: >=3.12
Requires-Dist: classconfig~=1.0.5
Requires-Dist: Jinja2~=3.1.4
Requires-Dist: openai~=1.57.0
Requires-Dist: inquirer~=3.4.0
Requires-Dist: tiktoken~=0.8.0
Requires-Dist: tqdm~=4.66.5
Requires-Dist: numpy~=1.26.4
Requires-Dist: datasets~=3.6.0
Requires-Dist: json-repair
Requires-Dist: ollama~=0.4.7
Requires-Dist: segmentedstring~=1.0.1
Requires-Dist: pillow~=10.4.0
Requires-Dist: requests~=2.32.3
Requires-Dist: pydantic~=2.11.7
